{
    "id": "bearcms/search-box-element-addon",
    "name": "Search element",
    "description": "Add search functionality to your website with this addon. You will be able to add a search box element in the content zones of your website. Every change you make will be visible in the search results in a couple of minutes.",
    "author": {
        "name": "Bear CMS",
        "email": "support@bearcms.com",
        "url": "https://bearcms.com/"
    },
    "media": [
        {
            "filename": "/assets/1.png",
            "width": 1890,
            "height": 1404
        }
    ]
}